uamt/__init__.py
uamt/uamtto.cpython-312.so
uamt-1.3.1.dist-info/entry_points.txt
uamt-1.3.1.dist-info/WHEEL
uamt-1.3.1.dist-info/METADATA
uamt-1.3.1.dist-info/RECORD
