Metadata-Version: 2.4
Name: uamt
Version: 1.3.1
Summary: Auto Android App Modding Tool
Author: uamt
Requires-Python: >=3.8
